NiukeKuaixiaoXingyeMingqiBiMianshiXiaozhaoQiuzhiGonglve20212022Fix1/README.md
NiukeKuaixiaoXingyeMingqiBiMianshiXiaozhaoQiuzhiGonglve20212022Fix1/__init__.py
NiukeKuaixiaoXingyeMingqiBiMianshiXiaozhaoQiuzhiGonglve20212022Fix1/__main__.py
NiukeKuaixiaoXingyeMingqiBiMianshiXiaozhaoQiuzhiGonglve20212022Fix1/file.epub
NiukeKuaixiaoXingyeMingqiBiMianshiXiaozhaoQiuzhiGonglve20212022Fix1/index.html
NiukeKuaixiaoXingyeMingqiBiMianshiXiaozhaoQiuzhiGonglve20212022Fix1/css/__init__.py
NiukeKuaixiaoXingyeMingqiBiMianshiXiaozhaoQiuzhiGonglve20212022Fix1/css/annotations.css
NiukeKuaixiaoXingyeMingqiBiMianshiXiaozhaoQiuzhiGonglve20212022Fix1/css/main.css
NiukeKuaixiaoXingyeMingqiBiMianshiXiaozhaoQiuzhiGonglve20212022Fix1/css/normalize.css
NiukeKuaixiaoXingyeMingqiBiMianshiXiaozhaoQiuzhiGonglve20212022Fix1/css/popup.css
NiukeKuaixiaoXingyeMingqiBiMianshiXiaozhaoQiuzhiGonglve20212022Fix1/font/__init__.py
NiukeKuaixiaoXingyeMingqiBiMianshiXiaozhaoQiuzhiGonglve20212022Fix1/font/fontello.eot
NiukeKuaixiaoXingyeMingqiBiMianshiXiaozhaoQiuzhiGonglve20212022Fix1/font/fontello.svg
NiukeKuaixiaoXingyeMingqiBiMianshiXiaozhaoQiuzhiGonglve20212022Fix1/font/fontello.ttf
NiukeKuaixiaoXingyeMingqiBiMianshiXiaozhaoQiuzhiGonglve20212022Fix1/font/fontello.woff
NiukeKuaixiaoXingyeMingqiBiMianshiXiaozhaoQiuzhiGonglve20212022Fix1/img/__init__.py
NiukeKuaixiaoXingyeMingqiBiMianshiXiaozhaoQiuzhiGonglve20212022Fix1/img/annotator-glyph-sprite.png
NiukeKuaixiaoXingyeMingqiBiMianshiXiaozhaoQiuzhiGonglve20212022Fix1/img/annotator-icon-sprite.png
NiukeKuaixiaoXingyeMingqiBiMianshiXiaozhaoQiuzhiGonglve20212022Fix1/img/apple-touch-icon.png
NiukeKuaixiaoXingyeMingqiBiMianshiXiaozhaoQiuzhiGonglve20212022Fix1/img/cancelfullscreen.png
NiukeKuaixiaoXingyeMingqiBiMianshiXiaozhaoQiuzhiGonglve20212022Fix1/img/close.png
NiukeKuaixiaoXingyeMingqiBiMianshiXiaozhaoQiuzhiGonglve20212022Fix1/img/fullscreen.png
NiukeKuaixiaoXingyeMingqiBiMianshiXiaozhaoQiuzhiGonglve20212022Fix1/img/loader.gif
niuke_kuaixiao_xingye_mingqi_bi_mianshi_xiaozhao_qiuzhi_gonglve_2021_2022_fix1-2025.3.25.0.dist-info/METADATA
niuke_kuaixiao_xingye_mingqi_bi_mianshi_xiaozhao_qiuzhi_gonglve_2021_2022_fix1-2025.3.25.0.dist-info/WHEEL
niuke_kuaixiao_xingye_mingqi_bi_mianshi_xiaozhao_qiuzhi_gonglve_2021_2022_fix1-2025.3.25.0.dist-info/entry_points.txt
niuke_kuaixiao_xingye_mingqi_bi_mianshi_xiaozhao_qiuzhi_gonglve_2021_2022_fix1-2025.3.25.0.dist-info/top_level.txt
niuke_kuaixiao_xingye_mingqi_bi_mianshi_xiaozhao_qiuzhi_gonglve_2021_2022_fix1-2025.3.25.0.dist-info/RECORD
